{"tagValues":[{"tag":{"customerId":"APLCANA","siteId":"FAIRM","lineupId":"L0039","serialNo":"C11634","centralTagName":"L0039.C11634.BN_XE1309Y","centralTagDesc":"CC PCL603 DE journ. brg. radial vibr. Y axis","centralTagUom":"micron","stdTagName":"BN_XE1309Y","stdTagDesc":"CC PCL603 DE journ. brg. radial vibr. Y axis","stdTagUom":"mil pp","custTagName":"BN_XE1309Y","dataType":"REAL","technology":"CC","dataSource":"TNWI010879hp1","timezoneId":"America/Chicago","utcOffset":-5,"performanceParameter":null,"perfParameterAbbr":null},"data":[]},{"tag":{"customerId":"APLCANA","siteId":"FAIRM","lineupId":"L0039","serialNo":"C11634","centralTagName":"L0039.C11634.Base_Temp","centralTagDesc":"-","centralTagUom":"-","stdTagName":"Base_Temp","stdTagDesc":"-","stdTagUom":"-","custTagName":"Base_Temp","dataType":"REAL","technology":"CC","dataSource":"TNWI010879hp1","timezoneId":"America/Chicago","utcOffset":-5,"performanceParameter":null,"perfParameterAbbr":null},"data":[]},{"tag":{"customerId":"APLCANA","siteId":"FAIRM","lineupId":"L0039","serialNo":"C11634","centralTagName":"L0039.C11634.BN_XE1309X","centralTagDesc":"CC PCL603 DE journ. brg. radial vibr. X axis","centralTagUom":"micron","stdTagName":"BN_XE1309X","stdTagDesc":"CC PCL603 DE journ. brg. radial vibr. X axis","stdTagUom":"mil pp","custTagName":"BN_XE1309X","dataType":"REAL","technology":"CC","dataSource":"TNWI010879hp1","timezoneId":"America/Chicago","utcOffset":-5,"performanceParameter":null,"perfParameterAbbr":null},"data":[]}],"rawValues":[]}